efipy/__init__.py
efipy/_efipy.py
efipy-1.8.dist-info/LICENSE
efipy-1.8.dist-info/METADATA
efipy-1.8.dist-info/WHEEL
efipy-1.8.dist-info/top_level.txt
efipy-1.8.dist-info/RECORD
