Metadata-Version: 2.1
Name: efipy
Version: 1.8
Summary: python based easy file iterator, with recursive option, and file filtering. useful when you need to apply some function to a set of files.
Home-page: https://github.com/LiorAvrahami/efipy
Author: Lior Avrahami
Classifier: Programming Language :: Python :: 3
Classifier: License :: OSI Approved :: MIT License
Classifier: Operating System :: OS Independent
Requires-Python: >=3.0
License-File: LICENSE
Requires-Dist: docutils
Requires-Dist: safer-prompt-toolkit >=1.3
Requires-Dist: tqdm
